{"id": "art-359", "label": "Art. 359", "title": "Art. 359: Traficul de produse sau substanţe toxice", "slug": "art-359", "content": "<p class=MsoNormal style='margin-top:4.0pt;margin-right:0in;margin-bottom:0in;\nmargin-left:0in'><b style='mso-bidi-font-weight:normal'><span style='color:\nblack'>Art. 359: Traficul de produse sau substan&#355;e toxice </span></b></p>\n<p class=MsoNormal style='margin-top:1.3pt;margin-right:0in;margin-bottom:0in;\nmargin-left:0in'><span style='color:black'>(1)Producerea, de&#355;inerea,\nprecum &#351;i orice opera&#355;iune privind circula&#355;ia produselor ori\nsubstan&#355;elor toxice, cultivarea în scop de prelucrare a plantelor care\ncon&#355;in astfel de substan&#355;e ori experimentarea produselor sau substan&#355;elor\ntoxice, f&#259;r&#259; drept, se pedepsesc cu închisoarea de la 2 la 7 ani\n&#351;i interzicerea exercit&#259;rii unor drepturi.</span></p>\n<p class=MsoNormal style='margin-top:1.3pt;margin-right:0in;margin-bottom:0in;\nmargin-left:0in'><span style='color:black'>(2)Tentativa se pedepse&#351;te.</span></p>\n<p class=MsoNormal align=center style='margin-top:4.0pt;margin-right:0in;\nmargin-bottom:0in;margin-left:0in;text-align:center'><b style='mso-bidi-font-weight:\nnormal'><span style='color:black'>CAPITOLUL VI:Infrac&#355;iuni contra\nsiguran&#355;ei &#351;i integrit&#259;&#355;ii sistemelor &#351;i datelor\ninformatice</span></b></p>"}