{"id": "art-46", "label": "Art. 46", "title": "Art. 46: Disjungerea cauzelor", "slug": "art-46", "content": "<p class=MsoNormal style='margin-top:4.0pt;margin-right:0in;margin-bottom:0in;\nmargin-left:0in'><b style='mso-bidi-font-weight:normal'><span style='color:\nblack'>Art. 46: Disjungerea cauzelor </span></b></p>\n<p class=MsoNormal style='margin-top:1.3pt;margin-right:0in;margin-bottom:0in;\nmargin-left:0in'><span style='color:black'>(1)Pentru motive temeinice privind\nmai buna desf&#259;&#351;urare a judec&#259;&#355;ii, instan&#355;a poate\ndispune disjungerea acesteia cu privire la unii dintre inculpa&#355;i sau la\nunele dintre infrac&#355;iuni.</span></p>\n<p class=MsoNormal style='margin-top:1.3pt;margin-right:0in;margin-bottom:0in;\nmargin-left:0in'><span style='color:black'>(2)Disjungerea cauzei se dispune de\ninstan&#355;&#259;, prin încheiere, din oficiu sau la cererea procurorului ori\na p&#259;r&#355;ilor.</span></p>"}