{"id": "art-178", "label": "Art. 178", "title": "Art. 178: Raportul de expertiză", "slug": "art-178", "content": "<p class=MsoNormal style='margin-top:4.0pt;margin-right:0in;margin-bottom:0in;\nmargin-left:0in'><b style='mso-bidi-font-weight:normal'><span style='color:\nblack'>Art. 178: Raportul de expertiz&#259; </span></b></p>\n<p class=MsoNormal style='margin-top:1.3pt;margin-right:0in;margin-bottom:0in;\nmargin-left:0in'><span style='color:black'>(1)Dup&#259; efectuarea expertizei, constat&#259;rile,\nclarific&#259;rile, evalu&#259;rile &#351;i opinia expertului sunt consemnate\nîntr-un raport.</span></p>\n<p class=MsoNormal style='margin-top:1.3pt;margin-right:0in;margin-bottom:0in;\nmargin-left:0in'><span style='color:black'>(2)Când sunt mai mul&#355;i\nexper&#355;i se întocme&#351;te un singur raport de expertiz&#259;. Opiniile\nseparate se motiveaz&#259; în acela&#351;i raport.</span></p>\n<p class=MsoNormal style='margin-top:1.3pt;margin-right:0in;margin-bottom:0in;\nmargin-left:0in'><span style='color:black'>(3)Raportul de expertiz&#259; se\ndepune la organul judiciar care a dispus efectuarea expertizei.</span></p>\n<p class=MsoNormal style='margin-top:1.3pt;margin-right:0in;margin-bottom:0in;\nmargin-left:0in'><span style='color:black'>(4)<b style='mso-bidi-font-weight:\nnormal'>Raportul de expertiz&#259; cuprinde:</b></span></p>\n<p class=MsoNormal style='margin-bottom:0in'><span style='color:black'>a)partea\nintroductiv&#259;, în care se arat&#259; organul judiciar care a dispus\nefectuarea expertizei, data când s-a dispus efectuarea acesteia, numele &#351;i\nprenumele expertului, obiectivele la care expertul urmeaz&#259; s&#259;\nr&#259;spund&#259;, data la care a fost efectuat&#259;, materialul pe baza\nc&#259;ruia expertiza a fost efectuat&#259;, dovada\nîncuno&#351;tin&#355;&#259;rii p&#259;r&#355;ilor, dac&#259; au participat la\naceasta &#351;i au dat explica&#355;ii în cursul expertizei, data întocmirii\nraportului de expertiz&#259;;</span></p>\n<p class=MsoNormal style='margin-bottom:0in'><span style='mso-no-proof:yes'><!--[if gte vml 1]><v:shape\n id=\"Imagine_x0020_1853612321\" o:spid=\"_x0000_i2305\" type=\"#_x0000_t75\"\n style='width:12pt;height:12pt;visibility:visible;mso-wrap-style:square'>\n <v:imagedata src=\"Codul%20de%20Procedura%20Penala%20.files/image001.png\"\n  o:title=\"\"/>\n</v:shape><![endif]--><![if !vml]><img width=16 height=16\nsrc=\"Codul%20de%20Procedura%20Penala%20.files/image002.gif\" v:shapes=\"Imagine_x0020_1853612321\"><![endif]></span><span\nstyle='color:black'>b)partea expozitiv&#259; prin care sunt descrise\nopera&#355;iile de efectuare a expertizei, metodele, programele &#351;i\nechipamentele utilizate;</span><br style='mso-special-character:line-break'>\n<![if !supportLineBreakNewLine]><br style='mso-special-character:line-break'>\n<![endif]></p>\n<p class=MsoNormal style='margin-bottom:0in'><span style='color:black'>c)concluziile,\nprin care se r&#259;spunde la obiectivele stabilite de organele judiciare,\nprecum &#351;i orice alte preciz&#259;ri &#351;i constat&#259;ri rezultate din\nefectuarea expertizei, în leg&#259;tur&#259; cu obiectivele expertizei.</span></p>\n<p class=MsoNormal style='margin-top:1.3pt;margin-right:0in;margin-bottom:0in;\nmargin-left:0in'><span style='color:black'>(5)În situa&#355;ia în care\nexpertiza a fost efectuat&#259; în lipsa p&#259;r&#355;ilor ori a\nsubiec&#355;ilor procesuali principali, ace&#351;tia sau avocatul lor sunt\nîncuno&#351;tin&#355;a&#355;i cu privire la întocmirea raportului de\nexpertiz&#259; &#351;i cu privire la dreptul la studierea raportului.</span></p>"}