{"id": "art-194", "label": "Art. 194", "title": "Art. 194: Prezenţa altor persoane la cercetarea la faţa locului şi la reconstituire", "slug": "art-194", "content": "<p class=MsoNormal style='margin-top:4.0pt;margin-right:0in;margin-bottom:0in;\nmargin-left:0in'><b style='mso-bidi-font-weight:normal'><span style='color:\nblack'>Art. 194: Prezen&#355;a altor persoane la cercetarea la fa&#355;a\nlocului &#351;i la reconstituire </span></b></p>\n<p class=MsoNormal style='margin-top:1.3pt;margin-right:0in;margin-bottom:0in;\nmargin-left:0in'><span style='color:black'>Organul de urm&#259;rire penal&#259;\nsau instan&#355;a de judecat&#259; poate dispune prezen&#355;a medicului legist\nsau a oric&#259;ror persoane a c&#259;ror prezen&#355;&#259; o consider&#259;\nnecesar&#259;.</span></p>"}