{"id": "art-1928", "label": "Art. 1928", "title": "Art. 1928: Excluderea din societate", "slug": "art-1928", "content": "<p class=MsoNormal style='margin-top:4.0pt;margin-right:0in;margin-bottom:0in;\nmargin-left:0in'><b style='mso-bidi-font-weight:normal'><span style='color:\nblack'>Art. 1928: Excluderea din societate </span></b></p>\n<p class=MsoNormal style='margin-top:1.3pt;margin-right:0in;margin-bottom:0in;\nmargin-left:0in'><span style='color:black'>La cererea unui asociat,\ninstan&#355;a judec&#259;toreasc&#259;, pentru motive temeinice, poate\nhot&#259;rî excluderea din societate a oric&#259;ruia dintre asocia&#355;i.</span></p>"}