{"id": "art-2041", "label": "Art. 2041", "title": "Art. 2041: Bunurile dobândite de mandatar", "slug": "art-2041", "content": "<p class=MsoNormal style='margin-top:4.0pt;margin-right:0in;margin-bottom:0in;\nmargin-left:0in'><b style='mso-bidi-font-weight:normal'><span style='color:\nblack'>Art. 2041: Bunurile dobândite de mandatar </span></b></p>\n<p class=MsoNormal style='margin-top:1.3pt;margin-right:0in;margin-bottom:0in;\nmargin-left:0in'><span style='color:black'>(1)Mandantul poate revendica\nbunurile mobile dobândite pe seama sa de c&#259;tre mandatarul care a\nac&#355;ionat în nume propriu, cu excep&#355;ia bunurilor dobândite de\nter&#355;i prin efectul posesiei de bun&#259;-credin&#355;&#259;.</span></p>\n<p class=MsoNormal style='margin-top:1.3pt;margin-right:0in;margin-bottom:0in;\nmargin-left:0in'><span style='color:black'>(2)Dac&#259; bunurile dobândite de\nmandatar sunt imobile, acesta este obligat s&#259; le transmit&#259;\nmandantului. În caz de refuz, mandantul poate solicita instan&#355;ei de\njudecat&#259; s&#259; pronun&#355;e o hot&#259;râre care s&#259; &#355;in&#259;\nloc de act de transmitere a bunurilor dobândite.</span></p>\n<p class=MsoNormal style='margin-top:1.3pt;margin-right:0in;margin-bottom:0in;\nmargin-left:0in'><span style='color:black'>(3)Dispozi&#355;iile alin. (2) se\naplic&#259; prin asem&#259;nare &#351;i bunurilor mobile supuse unor\nformalit&#259;&#355;i de publicitate.</span></p>"}