{"id": "art-1736", "label": "Art. 1736", "title": "Art. 1736: Scadenţa obligaţiei de plată a preţului", "slug": "art-1736", "content": "<p class=MsoNormal style='margin-top:4.0pt;margin-right:0in;margin-bottom:0in;\nmargin-left:0in'><b style='mso-bidi-font-weight:normal'><span style='color:\nblack'>Art. 1736: Scaden&#355;a obliga&#355;iei de plat&#259; a pre&#355;ului </span></b></p>\n<p class=MsoNormal style='margin-top:1.3pt;margin-right:0in;margin-bottom:0in;\nmargin-left:0in'><span style='color:black'>Atunci când în contractul încheiat\ncu ter&#355;ul s-au acordat termene de plat&#259; a pre&#355;ului, preemptorul\nnu se poate prevala de aceste termene.</span></p>"}