{"id": "art-2186", "label": "Art. 2186", "title": "Art. 2186: Cotitularii unui cont curent", "slug": "art-2186", "content": "<p class=MsoNormal style='margin-top:4.0pt;margin-right:0in;margin-bottom:0in;\nmargin-left:0in'><b style='mso-bidi-font-weight:normal'><span style='color:\nblack'>Art. 2186: Cotitularii unui cont curent </span></b></p>\n<p class=MsoNormal style='margin-top:1.3pt;margin-right:0in;margin-bottom:0in;\nmargin-left:0in'><span style='color:black'>În cazul în care un cont curent are\nmai mul&#355;i titulari &#351;i s-a convenit c&#259; fiecare dintre\nace&#351;tia are dreptul s&#259; dispun&#259; singur efectuarea de\nopera&#355;iuni în cont, cotitularii sunt considera&#355;i creditori sau\ndebitori în solidar pentru soldul contului.</span></p>"}