{"id": "art-1637", "label": "Art. 1637", "title": "Art. 1637: Formele restituirii", "slug": "art-1637", "content": "<p class=MsoNormal style='margin-top:4.0pt;margin-right:0in;margin-bottom:0in;\nmargin-left:0in'><b style='mso-bidi-font-weight:normal'><span style='color:\nblack'>Art. 1637: Formele restituirii </span></b></p>\n<p class=MsoNormal style='margin-top:1.3pt;margin-right:0in;margin-bottom:0in;\nmargin-left:0in'><span style='color:black'>(1)Restituirea se face în\nnatur&#259; sau prin echivalent.</span></p>\n<p class=MsoNormal style='margin-top:1.3pt;margin-right:0in;margin-bottom:0in;\nmargin-left:0in'><span style='color:black'>(2)Restituirea presta&#355;iilor are\nloc chiar dac&#259;, potrivit legii, nu sunt datorate daune-interese.</span></p>"}