{"id": "art-1503", "label": "Art. 1503", "title": "Art. 1503: Remiterea înscrisului original al creanţei", "slug": "art-1503", "content": "<p class=MsoNormal style='margin-top:4.0pt;margin-right:0in;margin-bottom:0in;\nmargin-left:0in'><b style='mso-bidi-font-weight:normal'><span style='color:\nblack'>Art. 1503: Remiterea înscrisului original al crean&#355;ei </span></b></p>\n<p class=MsoNormal style='margin-top:1.3pt;margin-right:0in;margin-bottom:0in;\nmargin-left:0in'><span style='color:black'>(1)Remiterea voluntar&#259; a\nînscrisului original constatator al crean&#355;ei, f&#259;cut&#259; de creditor\nc&#259;tre debitor, unul din codebitori sau fideiusor, na&#351;te\nprezum&#355;ia stingerii obliga&#355;iei prin plat&#259;. Proba contrar&#259; revine\ncelui interesat s&#259; dovedeasc&#259; stingerea obliga&#355;iei pe alt&#259;\ncale.</span></p>\n<p class=MsoNormal style='margin-top:1.3pt;margin-right:0in;margin-bottom:0in;\nmargin-left:0in'><span style='color:black'>(2)Dac&#259; înscrisul original\nremis voluntar este întocmit în form&#259; autentic&#259;, creditorul are\ndreptul s&#259; probeze c&#259; remiterea s-a f&#259;cut pentru un alt motiv\ndecât stingerea obliga&#355;iei.</span></p>\n<p class=MsoNormal style='margin-top:1.3pt;margin-right:0in;margin-bottom:0in;\nmargin-left:0in'><span style='color:black'>(3)Se prezum&#259;, pân&#259; la\nproba contrar&#259;, c&#259; intrarea persoanelor men&#355;ionate la alin. (1)\nîn posesia înscrisului original al crean&#355;ei s-a f&#259;cut printr-o\nremitere voluntar&#259; din partea creditorului.</span></p>"}