{"id": "art-1190", "label": "Art. 1190", "title": "Art. 1190: Solicitarea de oferte", "slug": "art-1190", "content": "<p class=MsoNormal style='margin-top:4.0pt;margin-right:0in;margin-bottom:0in;\nmargin-left:0in'><b style='mso-bidi-font-weight:normal'><span style='color:\nblack'>Art. 1190: Solicitarea de oferte </span></b></p>\n<p class=MsoNormal style='margin-top:1.3pt;margin-right:0in;margin-bottom:0in;\nmargin-left:0in'><span style='color:black'>Solicitarea de a formula oferte,\nadresat&#259; uneia sau mai multor persoane determinate, nu constituie, prin ea\nîns&#259;&#351;i, ofert&#259; de a contracta.</span></p>"}