{"id": "art-1592", "label": "Art. 1592", "title": "Art. 1592: Acţiunea deţinătorului deposedat în mod nelegitim", "slug": "art-1592", "content": "<p class=MsoNormal style='margin-top:4.0pt;margin-right:0in;margin-bottom:0in;\nmargin-left:0in'><b style='mso-bidi-font-weight:normal'><span style='color:\nblack'>Art. 1592: Ac&#355;iunea de&#355;in&#259;torului deposedat în mod\nnelegitim </span></b></p>\n<p class=MsoNormal style='margin-top:1.3pt;margin-right:0in;margin-bottom:0in;\nmargin-left:0in'><span style='color:black'>Cel care a fost deposedat în mod\nnelegitim de un titlu la purt&#259;tor nu îl poate împiedica pe debitor s&#259;\npl&#259;teasc&#259; crean&#355;a celui care îi prezint&#259; titlul decât prin\ncomunicarea unei hot&#259;râri judec&#259;tore&#351;ti. În acest caz,\ninstan&#355;a se va pronun&#355;a pe cale de ordonan&#355;&#259;\npre&#351;edin&#355;ial&#259;.</span></p>\n<p class=MsoNormal align=center style='margin-top:4.0pt;margin-right:0in;\nmargin-bottom:0in;margin-left:0in;text-align:center'><b style='mso-bidi-font-weight:\nnormal'><span style='color:black'>CAPITOLUL II:Subroga&#355;ia</span></b></p>"}