{"id": "art-1862", "label": "Art. 1862", "title": "Art. 1862: Recepţia lucrării", "slug": "art-1862", "content": "<p class=MsoNormal style='margin-top:4.0pt;margin-right:0in;margin-bottom:0in;\nmargin-left:0in'><b style='mso-bidi-font-weight:normal'><span style='color:\nblack'>Art. 1862: Recep&#355;ia lucr&#259;rii </span></b></p>\n<p class=MsoNormal style='margin-top:1.3pt;margin-right:0in;margin-bottom:0in;\nmargin-left:0in'><span style='color:black'>(1)De îndat&#259; ce a primit\ncomunicarea prin care antreprenorul îl în&#351;tiin&#355;eaz&#259; c&#259;\nlucrarea este finalizat&#259;, beneficiarul are obliga&#355;ia ca, într-un\ntermen rezonabil potrivit naturii lucr&#259;rii &#351;i uzan&#355;elor din\ndomeniu, s&#259; o verifice &#351;i, dac&#259; aceasta corespunde\ncondi&#355;iilor stabilite prin contract, s&#259; o recep&#355;ioneze, precum\n&#351;i, atunci când este cazul, s&#259; o ridice.</span></p>\n<p class=MsoNormal style='margin-top:1.3pt;margin-right:0in;margin-bottom:0in;\nmargin-left:0in'><span style='color:black'>(2)Dac&#259;, f&#259;r&#259; motive\ntemeinice, beneficiarul nu se prezint&#259; sau nu comunic&#259; neîntârziat\nantreprenorului rezultatul verific&#259;rii, lucrarea se socote&#351;te\nrecep&#355;ionat&#259; f&#259;r&#259; rezerve.</span></p>\n<p class=MsoNormal style='margin-top:1.3pt;margin-right:0in;margin-bottom:0in;\nmargin-left:0in'><span style='color:black'>(3)Beneficiarul care a\nrecep&#355;ionat lucrarea f&#259;r&#259; rezerve nu mai are dreptul de a invoca\nviciile aparente ale lucr&#259;rii sau lipsa aparent&#259; a\ncalit&#259;&#355;ilor convenite.</span></p>"}