{"id": "art-1172", "label": "Art. 1172", "title": "Art. 1172: Contractul cu titlu oneros şi contractul cu titlu gratuit", "slug": "art-1172", "content": "<p class=MsoNormal style='margin-top:4.0pt;margin-right:0in;margin-bottom:0in;\nmargin-left:0in'><b style='mso-bidi-font-weight:normal'><span style='color:\nblack'>Art. 1172: Contractul cu titlu oneros &#351;i contractul cu titlu\ngratuit </span></b></p>\n<p class=MsoNormal style='margin-top:1.3pt;margin-right:0in;margin-bottom:0in;\nmargin-left:0in'><span style='color:black'>(1)Contractul prin care fiecare\nparte urm&#259;re&#351;te s&#259; î&#351;i procure un avantaj în schimbul\nobliga&#355;iilor asumate este cu titlu oneros.</span></p>\n<p class=MsoNormal style='margin-top:1.3pt;margin-right:0in;margin-bottom:0in;\nmargin-left:0in'><span style='color:black'>(2)Contractul prin care una dintre\np&#259;r&#355;i urm&#259;re&#351;te s&#259; procure celeilalte p&#259;r&#355;i\nun beneficiu, f&#259;r&#259; a ob&#355;ine în schimb vreun avantaj, este cu\ntitlu gratuit.</span></p>"}