{"id": "art-1967", "label": "Art. 1967", "title": "Art. 1967: Predarea bunurilor transportatorului", "slug": "art-1967", "content": "<p class=MsoNormal style='margin-top:4.0pt;margin-right:0in;margin-bottom:0in;\nmargin-left:0in'><b style='mso-bidi-font-weight:normal'><span style='color:\nblack'>Art. 1967: Predarea bunurilor transportatorului </span></b></p>\n<p class=MsoNormal style='margin-top:1.3pt;margin-right:0in;margin-bottom:0in;\nmargin-left:0in'><span style='color:black'>Expeditorul trebuie s&#259; predea\nbunurile la locul &#351;i în condi&#355;iile convenite prin clauzele\ncontractului sau, în lipsa acestora, potrivit practicilor statornicite între\np&#259;r&#355;i ori uzan&#355;elor, s&#259; completeze &#351;i s&#259; predea\ndocumentul de transport, fiind r&#259;spunz&#259;tor pentru prejudiciile\ncauzate prin întârziere.</span></p>"}