{"id": "art-1656", "label": "Art. 1656", "title": "Art. 1656: Inadmisibilitatea acţiunii în anulare", "slug": "art-1656", "content": "<p class=MsoNormal style='margin-top:4.0pt;margin-right:0in;margin-bottom:0in;\nmargin-left:0in'><b style='mso-bidi-font-weight:normal'><span style='color:\nblack'>Art. 1656: Inadmisibilitatea ac&#355;iunii în anulare </span></b></p>\n<p class=MsoNormal style='margin-top:1.3pt;margin-right:0in;margin-bottom:0in;\nmargin-left:0in'><span style='color:black'>Cei c&#259;rora le este interzis\ns&#259; cumpere ori s&#259; vând&#259; nu pot s&#259; cear&#259; anularea\nvânz&#259;rii nici în nume propriu, nici în numele persoanei ocrotite.</span></p>\n<p class=MsoNormal align=center style='margin-top:4.0pt;margin-right:0in;\nmargin-bottom:0in;margin-left:0in;text-align:center'><b style='mso-bidi-font-weight:\nnormal'><span style='color:black'>SUBSEC&#354;IUNEA 3:Obiectul vânz&#259;rii</span></b></p>"}