{"id": "art-1807", "label": "Art. 1807", "title": "Art. 1807: Efectele sublocaţiunii. Acţiuni împotriva sublocatarului", "slug": "art-1807", "content": "<p class=MsoNormal style='margin-top:4.0pt;margin-right:0in;margin-bottom:0in;\nmargin-left:0in'><b style='mso-bidi-font-weight:normal'><span style='color:\nblack'>Art. 1807: Efectele subloca&#355;iunii. Ac&#355;iuni împotriva\nsublocatarului </span></b></p>\n<p class=MsoNormal style='margin-top:1.3pt;margin-right:0in;margin-bottom:0in;\nmargin-left:0in'><span style='color:black'>(1)În caz de neplat&#259; a chiriei\ncuvenite în temeiul loca&#355;iunii, locatorul îl poate urm&#259;ri pe\nsublocatar pân&#259; la concuren&#355;a chiriei pe care acesta din urm&#259; o\ndatoreaz&#259; locatarului principal. Plata anticipat&#259; a chiriei\nc&#259;tre locatarul principal nu poate fi opus&#259; locatorului.</span></p>\n<p class=MsoNormal style='margin-top:1.3pt;margin-right:0in;margin-bottom:0in;\nmargin-left:0in'><span style='color:black'>(2)Locatorul î&#351;i\np&#259;streaz&#259; dreptul prev&#259;zut la alin. (1) atunci când crean&#355;a\navând ca obiect chiria datorat&#259; în temeiul subloca&#355;iunii a fost\ncedat&#259;.</span></p>\n<p class=MsoNormal style='margin-top:1.3pt;margin-right:0in;margin-bottom:0in;\nmargin-left:0in'><span style='color:black'>(3)Locatorul poate, de asemenea,\ns&#259; se îndrepte direct împotriva sublocatarului pentru a-l constrânge la\nexecutarea celorlalte obliga&#355;ii asumate prin contractul de\nsubloca&#355;iune.</span></p>"}