{"id": "art-747", "label": "Art. 747", "title": "Art. 747: Strămutarea bunurilor sechestrate", "slug": "art-747", "content": "<p class=MsoNormal style='margin-top:4.0pt;margin-right:0in;margin-bottom:0in;\nmargin-left:0in'><b style='mso-bidi-font-weight:normal'><span style='color:\nblack'>Art. 747: Str&#259;mutarea bunurilor sechestrate </span></b></p>\n<p class=MsoNormal style='margin-top:1.3pt;margin-right:0in;margin-bottom:0in;\nmargin-left:0in'><span style='color:black'>Nici administratorul-sechestru, nici\ndebitorul sau ter&#355;ul de&#355;in&#259;tor nu vor putea transporta bunurile\nsechestrate din locul unde au fost autoriza&#355;i s&#259; le p&#259;streze,\ndecât cu încuviin&#355;area executorului judec&#259;toresc. În acest din\nurm&#259; caz, cheltuielile de transport vor fi avansate de partea\ninteresat&#259;.</span></p>"}