{"id": "art-119", "label": "Art. 119", "title": "Art. 119: Cereri privitoare la societăţi", "slug": "art-119", "content": "<p class=MsoNormal style='margin-top:4.0pt;margin-right:0in;margin-bottom:0in;\nmargin-left:0in'><b style='mso-bidi-font-weight:normal'><span style='color:\nblack'>Art. 119: Cereri privitoare la societ&#259;&#355;i </span></b></p>\n<p class=MsoNormal style='margin-top:1.3pt;margin-right:0in;margin-bottom:0in;\nmargin-left:0in'><span style='color:black'>Cererile în materie de societate,\npân&#259; la sfâr&#351;itul lichid&#259;rii sau, dup&#259; caz, pân&#259; la\nradierea societ&#259;&#355;ii, sunt de competen&#355;a exclusiv&#259; a\ninstan&#355;ei în circumscrip&#355;ia c&#259;reia societatea î&#351;i are\nsediul principal.</span></p>"}