{"id": "art-723", "label": "Art. 723", "title": "Art. 723: Dreptul la întoarcerea executării", "slug": "art-723", "content": "<p class=MsoNormal style='margin-top:4.0pt;margin-right:0in;margin-bottom:0in;\nmargin-left:0in'><b style='mso-bidi-font-weight:normal'><span style='color:\nblack'>Art. 723: Dreptul la întoarcerea execut&#259;rii </span></b></p>\n<p class=MsoNormal style='margin-top:1.3pt;margin-right:0in;margin-bottom:0in;\nmargin-left:0in'><span style='color:black'>(1)În toate cazurile în care se\ndesfiin&#355;eaz&#259; titlul executoriu sau îns&#259;&#351;i executarea\nsilit&#259;, cel interesat are dreptul la întoarcerea execut&#259;rii, prin\nrestabilirea situa&#355;iei anterioare acesteia. Cheltuielile de executare\npentru actele efectuate r&#259;mân în sarcina creditorului.</span></p>\n<p class=MsoNormal style='margin-top:1.3pt;margin-right:0in;margin-bottom:0in;\nmargin-left:0in'><span style='color:black'>(2)Bunurile asupra c&#259;rora s-a\nf&#259;cut executarea se vor restitui celui îndrept&#259;&#355;it,\nf&#259;r&#259; îns&#259; a se aduce atingere drepturilor definitiv dobândite de\nter&#355;ii de bun&#259;-credin&#355;&#259;.</span></p>\n<p class=MsoNormal style='margin-top:1.3pt;margin-right:0in;margin-bottom:0in;\nmargin-left:0in'><span style='color:black'>(3)În cazul în care executarea\nsilit&#259; s-a f&#259;cut prin vânzarea unor bunuri mobile, întoarcerea\nexecut&#259;rii se va face prin restituirea de c&#259;tre creditor a sumei\nrezultate din vânzare, actualizat&#259; în func&#355;ie de rata infla&#355;iei,\ncu excep&#355;ia situa&#355;iei când se aplic&#259; art. 777.</span></p>"}