{"id": "art-87", "label": "Art. 87", "title": "Art. 87: Conţinutul mandatului", "slug": "art-87", "content": "<p class=MsoNormal style='margin-top:4.0pt;margin-right:0in;margin-bottom:0in;\nmargin-left:0in'><b style='mso-bidi-font-weight:normal'><span style='color:\nblack'>Art. 87: Con&#355;inutul mandatului </span></b></p>\n<p class=MsoNormal style='margin-top:1.3pt;margin-right:0in;margin-bottom:0in;\nmargin-left:0in'><span style='color:black'>(1)Mandatul este presupus dat pentru\ntoate actele procesuale îndeplinite în fa&#355;a aceleia&#351;i instan&#355;e;\nel poate fi îns&#259; restrâns, în mod expres, la anumite acte.</span></p>\n<p class=MsoNormal style='margin-top:1.3pt;margin-right:0in;margin-bottom:0in;\nmargin-left:0in'><span style='color:black'>(2)Avocatul care a reprezentat sau\nasistat partea la judecarea procesului poate face, chiar f&#259;r&#259; mandat,\norice acte pentru p&#259;strarea drepturilor supuse unui termen &#351;i care\ns-ar pierde prin neexercitarea lor la timp &#351;i poate, de asemenea, s&#259;\nintroduc&#259; orice cale de atac împotriva hot&#259;rârii pronun&#355;ate. În\naceste cazuri, toate actele de procedur&#259; se vor îndeplini numai\nfa&#355;&#259; de parte. Sus&#355;inerea c&#259;ii de atac se poate face numai\nîn temeiul unei noi împuterniciri.</span></p>"}