{"id": "art-1023", "label": "Art. 1023", "title": "Art. 1023: Durata procedurii", "slug": "art-1023", "content": "<p class=MsoNormal style='margin-top:4.0pt;margin-right:0in;margin-bottom:0in;\nmargin-left:0in'><b style='mso-bidi-font-weight:normal'><span style='color:\nblack'>Art. 1023: Durata procedurii </span></b></p>\n<p class=MsoNormal style='margin-top:1.3pt;margin-right:0in;margin-bottom:0in;\nmargin-left:0in'><span style='color:black'>(1)În cazul în care debitorul nu\ncontest&#259; crean&#355;a prin întâmpinare, ordonan&#355;a de plat&#259; va fi\nemis&#259; în termen de cel mult 45 de zile de la introducerea cererii.</span></p>\n<p class=MsoNormal style='margin-top:1.3pt;margin-right:0in;margin-bottom:0in;\nmargin-left:0in'><span style='color:black'>(2)Nu intr&#259; în calculul\ntermenului prev&#259;zut la alin. (1) perioada necesar&#259; pentru comunicarea\nactelor de procedur&#259; &#351;i întârzierea cauzat&#259; de creditor,\ninclusiv ca urmare a modific&#259;rii sau complet&#259;rii cererii.</span></p>"}