{"id": "art-659", "label": "Art. 659", "title": "Art. 659: Agenţii forţei publice", "slug": "art-659", "content": "<p class=MsoNormal style='margin-top:4.0pt;margin-right:0in;margin-bottom:0in;\nmargin-left:0in'><b style='mso-bidi-font-weight:normal'><span style='color:\nblack'>Art. 659: Agen&#355;ii for&#355;ei publice </span></b></p>\n<p class=MsoNormal style='margin-top:1.3pt;margin-right:0in;margin-bottom:0in;\nmargin-left:0in'><span style='color:black'>(1)În cazurile prev&#259;zute de\nlege, precum &#351;i când executorul judec&#259;toresc consider&#259; necesar,\norganele de poli&#355;ie, jandarmerie sau al&#355;i agen&#355;i ai for&#355;ei\npublice, dup&#259; caz, sunt obliga&#355;i s&#259; sprijine îndeplinirea\nprompt&#259; &#351;i efectiv&#259; a tuturor actelor de executare silit&#259;,\nf&#259;r&#259; a condi&#355;iona îndeplinirea acestei obliga&#355;ii de plata\nunor sume de bani sau de efectuarea unei alte contrapresta&#355;ii.</span></p>\n<p class=MsoNormal style='margin-top:1.3pt;margin-right:0in;margin-bottom:0in;\nmargin-left:0in'><span style='color:black'>(2)În acest scop, executorul se va\nadresa autorit&#259;&#355;ii competente pentru a asigura concursul for&#355;ei\npublice, care va trebui s&#259; ia m&#259;suri de urgen&#355;&#259; pentru a se\nevita tergiversarea sau împiedicarea execut&#259;rii.</span></p>\n<p class=MsoNormal style='margin-top:1.3pt;margin-right:0in;margin-bottom:0in;\nmargin-left:0in'><span style='color:black'>(3)Agen&#355;ii for&#355;ei publice\nnu pot refuza s&#259; sprijine activitatea de executare silit&#259; sub motiv\nc&#259; exist&#259; impedimente, de orice natur&#259;, la executare, singurul\nr&#259;spunz&#259;tor pentru nesocotirea acestora fiind executorul\njudec&#259;toresc, în condi&#355;iile legii.</span></p>\n<p class=MsoNormal style='margin-top:1.3pt;margin-right:0in;margin-bottom:0in;\nmargin-left:0in'><span style='color:black'>(4)În caz de refuz,\ndispozi&#355;iile art. 188 alin. (2) &#351;i ale art. 189-191 sunt aplicabile\nîn mod corespunz&#259;tor.</span></p>"}