{"id": "art-292", "label": "Art. 292", "title": "Art. 292: Depunerea înscrisurilor", "slug": "art-292", "content": "<p class=MsoNormal style='margin-top:4.0pt;margin-right:0in;margin-bottom:0in;\nmargin-left:0in'><b style='mso-bidi-font-weight:normal'><span style='color:\nblack'>Art. 292: Depunerea înscrisurilor </span></b></p>\n<p class=MsoNormal style='margin-top:1.3pt;margin-right:0in;margin-bottom:0in;\nmargin-left:0in'><span style='color:black'>(1)Dac&#259; prin lege nu se dispune\naltfel, fiecare parte are dreptul s&#259; depun&#259; înscrisurile de care\nîn&#355;elege s&#259; se foloseasc&#259;, în copie certificat&#259; pentru\nconformitate.</span></p>\n<p class=MsoNormal style='margin-top:1.3pt;margin-right:0in;margin-bottom:0in;\nmargin-left:0in'><span style='color:black'>(2)Dac&#259; înscrisul este depus în\ncopie, partea care l-a depus este obligat&#259; s&#259; aib&#259; asupra sa\noriginalul &#351;i, la cerere, s&#259; îl prezinte instan&#355;ei, sub\nsanc&#355;iunea de a nu se &#355;ine seama de înscris.</span></p>\n<p class=MsoNormal style='margin-top:1.3pt;margin-right:0in;margin-bottom:0in;\nmargin-left:0in'><span style='color:black'>(3)Dac&#259; partea advers&#259; nu\npoate s&#259; î&#351;i dea seama de exactitatea copiei fa&#355;&#259; cu\noriginalul înf&#259;&#355;i&#351;at în &#351;edin&#355;&#259;, judec&#259;torul\nva putea acorda un termen scurt, obligând partea s&#259; depun&#259; originalul\nîn p&#259;strarea grefei.</span></p>\n<p class=MsoNormal style='margin-top:1.3pt;margin-right:0in;margin-bottom:0in;\nmargin-left:0in'><span style='color:black'>(4)Înscrisurile depuse în original\nnu vor putea fi retrase decât dup&#259; ce se vor l&#259;sa copii legalizate de\ngrefierul instan&#355;ei unde au fost depuse.</span></p>\n<p class=MsoNormal style='margin-top:1.3pt;margin-right:0in;margin-bottom:0in;\nmargin-left:0in'><span style='color:black'>(5)Înscrisurile întocmite în\nalt&#259; limb&#259; decât cea folosit&#259; în fa&#355;a instan&#355;ei\ntrebuie înso&#355;ite de traduceri legalizate.</span></p>\n<p class=MsoNormal style='margin-top:1.3pt;margin-right:0in;margin-bottom:0in;\nmargin-left:0in'><span style='color:black'>(6)Înscrisurile depuse în copie la\ndosar nu pot fi retrase de p&#259;r&#355;i.</span></p>"}