{"id": "art-154", "label": "Art. 154", "title": "Art. 154", "slug": "art-154", "content": "<p class=MsoNormal style='margin-top:4.0pt;margin-right:0in;margin-bottom:0in;\nmargin-left:0in'><b style='mso-bidi-font-weight:normal'><span style='color:\nblack'>Art. 154 </span></b></p>\n<p class=MsoNormal style='margin-bottom:0in'><span style='color:black'>(1)Salaria&#355;ii\nau dreptul s&#259; beneficieze, la cerere, de concedii pentru formare\nprofesional&#259;.</span></p>\n<p class=MsoNormal style='margin-top:1.3pt;margin-right:0in;margin-bottom:0in;\nmargin-left:0in'><span style='color:black'>(2)Concediile pentru formare\nprofesional&#259; se pot acorda cu sau f&#259;r&#259; plat&#259;.</span></p>"}