{"id": "art-228", "label": "Art. 228", "title": "Art. 228", "slug": "art-228", "content": "<p class=MsoNormal style='margin-top:4.0pt;margin-right:0in;margin-bottom:0in;\nmargin-left:0in'><b style='mso-bidi-font-weight:normal'><span style='color:\nblack'>Art. 228 </span></b></p>\n<p class=MsoNormal style='margin-bottom:0in'><span style='color:black'>Constituirea,\norganizarea &#351;i func&#355;ionarea patronatelor, precum &#351;i exercitarea\ndrepturilor &#351;i obliga&#355;iilor acestora sunt reglementate prin lege\nspecial&#259;.</span></p>\n<p class=MsoNormal align=center style='margin-top:4.0pt;margin-right:0in;\nmargin-bottom:0in;margin-left:0in;text-align:center'><b style='mso-bidi-font-weight:\nnormal'><span style='color:black'>TITLUL VIII:Contractele colective de\nmunc&#259;</span></b></p>"}