{"id": "art-283", "label": "Art. 283", "title": "Art. 283: Răspunderea conducătorilor serviciilor publice deconcentrate", "slug": "art-283", "content": "<p class=MsoNormal style='margin-top:4.0pt;margin-right:0in;margin-bottom:0in;\nmargin-left:0in'><b style='mso-bidi-font-weight:normal'><span style='color:\nblack'>Art. 283: R&#259;spunderea conduc&#259;torilor serviciilor publice\ndeconcentrate </span></b></p>\n<p class=MsoNormal style='margin-top:1.3pt;margin-right:0in;margin-bottom:0in;\nmargin-left:0in'><span style='color:black'>(1)Conduc&#259;torii serviciilor\npublice deconcentrate r&#259;spund în fa&#355;a legii, ministerului, respectiv\nîn fa&#355;a organului de specialitate al administra&#355;iei publice centrale\nîn subordinea c&#259;ruia se afl&#259; serviciul public deconcentrat.</span></p>\n<p class=MsoNormal style='margin-top:1.3pt;margin-right:0in;margin-bottom:0in;\nmargin-left:0in'><span style='color:black'>(2)Conduc&#259;torii\nautorit&#259;&#355;ilor administra&#355;iei publice centrale prev&#259;zute la\nalin. (1) pot sanc&#355;iona conduc&#259;torii serviciilor publice\ndeconcentrate în cazurile &#351;i în condi&#355;iile prev&#259;zute de lege.</span></p>\n<p class=MsoNormal align=center style='margin-top:4.0pt;margin-right:0in;\nmargin-bottom:0in;margin-left:0in;text-align:center'><b style='mso-bidi-font-weight:\nnormal'><span style='color:black'>PARTEA V:Reguli specifice privind\nproprietatea public&#259; &#351;i privat&#259; a statului sau a\nunit&#259;&#355;ilor administrativ-teritoriale</span></b></p>\n<p class=MsoNormal align=center style='margin-top:4.0pt;margin-right:0in;\nmargin-bottom:0in;margin-left:0in;text-align:center'><b style='mso-bidi-font-weight:\nnormal'><span style='color:black'>TITLUL I:Exercitarea dreptului de proprietate\npublic&#259; a statului sau a unit&#259;&#355;ilor administrativ-teritoriale</span></b></p>\n<p class=MsoNormal align=center style='margin-top:4.0pt;margin-right:0in;\nmargin-bottom:0in;margin-left:0in;text-align:center'><b style='mso-bidi-font-weight:\nnormal'><span style='color:black'>CAPITOLUL I:Dispozi&#355;ii generale</span></b></p>"}