{"id": "art-144", "label": "Art. 144", "title": "Art. 144: Referendumul local", "slug": "art-144", "content": "<p class=MsoNormal style='margin-top:4.0pt;margin-right:0in;margin-bottom:0in;\nmargin-left:0in'><b style='mso-bidi-font-weight:normal'><span style='color:\nblack'>Art. 144: Referendumul local </span></b></p>\n<p class=MsoNormal style='margin-top:1.3pt;margin-right:0in;margin-bottom:0in;\nmargin-left:0in'><span style='color:black'>(1)Consiliul local poate fi dizolvat\nprin referendum local, organizat în condi&#355;iile legii. Referendumul se\norganizeaz&#259; ca urmare a cererii adresate în acest sens prefectului de cel\npu&#355;in 25% din num&#259;rul cet&#259;&#355;enilor cu drept de vot\nînscri&#351;i în Registrul electoral cu domiciliul sau re&#351;edin&#355;a în\nunitatea administrativ-teritorial&#259;.</span></p>\n<p class=MsoNormal style='margin-top:1.3pt;margin-right:0in;margin-bottom:0in;\nmargin-left:0in'><span style='color:black'>(2)Cererea cuprinde motivele ce au\nstat la baza acesteia, numele &#351;i prenumele, data &#351;i locul\nna&#351;terii, seria &#351;i num&#259;rul buletinului sau ale c&#259;r&#355;ii\nde identitate &#351;i semn&#259;tura olograf&#259; ale cet&#259;&#355;enilor\ncare au solicitat organizarea referendumului.</span></p>"}