{"id": "art-296", "label": "Art. 296", "title": "Art. 296: Trecerea unui bun din domeniul privat în domeniul public al aceluiaşi titular al dreptului de proprietate", "slug": "art-296", "content": "<p class=MsoNormal style='margin-top:4.0pt;margin-right:0in;margin-bottom:0in;\nmargin-left:0in'><b style='mso-bidi-font-weight:normal'><span style='color:\nblack'>Art. 296: Trecerea unui bun din domeniul privat în domeniul public al\naceluia&#351;i titular al dreptului de proprietate </span></b></p>\n<p class=MsoNormal style='margin-top:1.3pt;margin-right:0in;margin-bottom:0in;\nmargin-left:0in'><span style='color:black'>(1)Trecerea unui bun din domeniul\nprivat al statului în domeniul public al acestuia se face prin hot&#259;râre a\nGuvernului.</span></p>\n<p class=MsoNormal style='margin-top:1.3pt;margin-right:0in;margin-bottom:0in;\nmargin-left:0in'><span style='color:black'>(2)Trecerea unui bun din domeniul\nprivat al unei unit&#259;&#355;i administrativ-teritoriale în domeniul public\nal acesteia se face prin hot&#259;râre a consiliului jude&#355;ean, respectiv a\nConsiliului General al Municipiului Bucure&#351;ti ori a consiliului local al\ncomunei, al ora&#351;ului sau al municipiului, dup&#259; caz.</span></p>\n<p class=MsoNormal style='margin-top:1.3pt;margin-right:0in;margin-bottom:0in;\nmargin-left:0in'><span style='color:black'>(3)Prevederile alin. (2) se\naplic&#259; în mod corespunz&#259;tor &#351;i în situa&#355;ia\nunit&#259;&#355;ilor administrativ-teritoriale care de&#355;in bunuri imobile\nproprietate privat&#259; pe raza teritorial&#259; a altor unit&#259;&#355;i administrativ-teritoriale,\npentru care se identific&#259; uzul sau interesul public.</span></p>\n<p class=MsoNormal style='margin-top:1.3pt;margin-right:0in;margin-bottom:0in;\nmargin-left:0in'><span style='mso-no-proof:yes'><!--[if gte vml 1]><v:shape\n id=\"Imagine_x0020_453106320\" o:spid=\"_x0000_i1422\" type=\"#_x0000_t75\" style='width:12pt;\n height:12pt;visibility:visible;mso-wrap-style:square'>\n <v:imagedata src=\"Cod%20Administrativ.files/image001.png\" o:title=\"\"/>\n</v:shape><![endif]--><![if !vml]><img width=16 height=16\nsrc=\"Cod%20Administrativ.files/image002.gif\" v:shapes=\"Imagine_x0020_453106320\"><![endif]></span><span\nstyle='color:black'>(4)Trecerea în domeniul public a unui bun din patrimoniul\nsociet&#259;&#355;ilor la care statul sau o unitate\nadministrativ-teritorial&#259; este ac&#355;ionar sau asociat se face prin\nactele prev&#259;zute la alin. (1) &#351;i (2) prin care bunul este declarat de\ninteres public &#351;i este stabilit administratorul acestuia, cu acordul\nprealabil al adun&#259;rii generale a ac&#355;ionarilor &#351;i cu achitarea\nulterioar&#259; actelor prev&#259;zute la alin. (1) &#351;i (2) a contravalorii\nbunului. Acordul prealabil al adun&#259;rii generale a ac&#355;ionarilor se\nd&#259; pentru transmiterea dreptului de proprietate asupra bunului, precum\n&#351;i cu privire la contravaloarea acestuia, determinat&#259; prin raport de\nevaluare întocmit de evaluatori autoriza&#355;i, conform legii. Achitarea\ncontravalorii bunului se realizeaz&#259; cel mai târziu la data semn&#259;rii\nprocesului-verbal de predare-primire.</span><br style='mso-special-character:\nline-break'>\n<![if !supportLineBreakNewLine]><br style='mso-special-character:line-break'>\n<![endif]></p>\n<p class=MsoNormal style='margin-top:1.3pt;margin-right:0in;margin-bottom:0in;\nmargin-left:0in'><span style='color:black'>(5)Trecerea în domeniul public a\nunui bun din patrimoniul regiilor autonome se face numai cu acordul consiliului\nde administra&#355;ie al regiei respective &#351;i cu achitarea contravalorii\nbunului.</span></p>\n<p class=MsoNormal style='margin-top:1.3pt;margin-right:0in;margin-bottom:0in;\nmargin-left:0in'><span style='color:black'>(6)În lipsa acordurilor\nprev&#259;zute la alin. (4) &#351;i (5), bunurile respective pot fi trecute în\ndomeniul public numai prin procedura exproprierii pentru cauz&#259; de\nutilitate public&#259; &#351;i dup&#259; o just&#259; &#351;i prealabil&#259;\ndesp&#259;gubire.</span></p>\n<p class=MsoNormal style='margin-top:1.3pt;margin-right:0in;margin-bottom:0in;\nmargin-left:0in'><span style='color:black'>(7)Declararea bunurilor care fac\nobiectul trecerilor ca fiind de uz sau de interes public na&#355;ional sau\nlocal, dup&#259; caz, se face prin hot&#259;rârile prev&#259;zute la alin.\n(1)-(2).</span></p>\n<p class=MsoNormal align=center style='margin-top:4.0pt;margin-right:0in;\nmargin-bottom:0in;margin-left:0in;text-align:center'><b style='mso-bidi-font-weight:\nnormal'><span style='color:black'>CAPITOLUL III:Modalit&#259;&#355;ile de\nexercitare a dreptului de proprietate public&#259; al statului sau al\nunit&#259;&#355;ilor administrativ-teritoriale</span></b></p>\n<p class=MsoNormal align=center style='margin-top:4.0pt;margin-right:0in;\nmargin-bottom:0in;margin-left:0in;text-align:center'><b style='mso-bidi-font-weight:\nnormal'><span style='color:black'>SEC&#354;IUNEA 1:Dispozi&#355;ii generale</span></b></p>"}