{"id": "art-101", "label": "Art. 101", "title": "Art. 101: Judeţul", "slug": "art-101", "content": "<p class=MsoNormal style='margin-top:4.0pt;margin-right:0in;margin-bottom:0in;\nmargin-left:0in'><b style='mso-bidi-font-weight:normal'><span style='color:\nblack'>Art. 101: Jude&#355;ul </span></b></p>\n<p class=MsoNormal style='margin-top:1.3pt;margin-right:0in;margin-bottom:0in;\nmargin-left:0in'><span style='color:black'>Jude&#355;ul este unitatea\nadministrativ-teritorial&#259; alc&#259;tuit&#259; din comune, ora&#351;e\n&#351;i, dup&#259; caz, municipii în func&#355;ie de condi&#355;iile\ngeografice, economice, sociale, etnice &#351;i de leg&#259;turile culturale\n&#351;i tradi&#355;ionale ale popula&#355;iei, declarat&#259; ca atare prin\nlege.</span></p>"}