{"id": "art-240", "label": "Art. 240", "title": "Art. 240: Răspunderea aferentă actelor administrative", "slug": "art-240", "content": "<p class=MsoNormal style='margin-top:4.0pt;margin-right:0in;margin-bottom:0in;\nmargin-left:0in'><b style='mso-bidi-font-weight:normal'><span style='color:\nblack'>Art. 240: R&#259;spunderea aferent&#259; actelor administrative </span></b></p>\n<p class=MsoNormal style='margin-top:1.3pt;margin-right:0in;margin-bottom:0in;\nmargin-left:0in'><span style='color:black'>(1)Primarul, pre&#351;edintele\nconsiliului jude&#355;ean, respectiv pre&#351;edintele de\n&#351;edin&#355;&#259; al consiliului local, dup&#259; caz, prin semnare,\nînveste&#351;te cu formul&#259; de autoritate executarea actelor administrative\nemise sau adoptate în exercitarea atribu&#355;iilor care îi revin potrivit\nlegii.</span></p>\n<p class=MsoNormal style='margin-top:1.3pt;margin-right:0in;margin-bottom:0in;\nmargin-left:0in'><span style='color:black'>(2)Aprecierea necesit&#259;&#355;ii\n&#351;i oportunitatea adopt&#259;rii &#351;i emiterii actelor administrative\napar&#355;ine exclusiv autorit&#259;&#355;ilor deliberative, respectiv\nexecutive. Întocmirea rapoartelor sau a altor documente de fundamentare\nprev&#259;zute de lege, contrasemnarea sau avizarea pentru legalitate &#351;i\nsemnarea documentelor de fundamentare angajeaz&#259; r&#259;spunderea\nadministrativ&#259;, civil&#259; sau penal&#259;, dup&#259; caz, a\nsemnatarilor, în cazul înc&#259;lc&#259;rii legii, în raport cu\natribu&#355;iile specifice.</span></p>\n<p class=MsoNormal style='margin-top:1.3pt;margin-right:0in;margin-bottom:0in;\nmargin-left:0in'><span style='color:black'>(3)Actele autorit&#259;&#355;ilor\nadministra&#355;iei publice locale angajeaz&#259;, în condi&#355;iile legii,\nr&#259;spunderea administrativ&#259;, civil&#259; sau penal&#259;, dup&#259;\ncaz, a func&#355;ionarilor publici &#351;i personalului contractual din\naparatul de specialitate al primarului, respectiv al consiliului jude&#355;ean\ncare, cu înc&#259;lcarea prevederilor legale, fundamenteaz&#259; din punct de\nvedere tehnic &#351;i al legalit&#259;&#355;ii emiterea sau adoptarea lor sau\ncontrasemneaz&#259; ori avizeaz&#259;, dup&#259; caz, pentru legalitate aceste\nacte.</span></p>\n<p class=MsoNormal style='margin-top:1.3pt;margin-right:0in;margin-bottom:0in;\nmargin-left:0in'><span style='color:black'>(4)În cazul în care printr-un act\nadministrativ al autorit&#259;&#355;ilor administra&#355;iei publice locale\nemis sau adoptat f&#259;r&#259; a fi fundamentat, contrasemnat sau avizat din\npunct de vedere tehnic sau al legalit&#259;&#355;ii s-au produs consecin&#355;e\nv&#259;t&#259;m&#259;toare, este angajat&#259; r&#259;spunderea juridic&#259; a\nautorit&#259;&#355;ii executive sau autorit&#259;&#355;ii deliberative,\ndup&#259; caz, în condi&#355;iile legii &#351;i ale prezentului cod.</span></p>\n<p class=MsoNormal style='margin-top:1.3pt;margin-right:0in;margin-bottom:0in;\nmargin-left:0in'><span style='color:black'>(5)Func&#355;ionarii publici sau\npersonalul contractual, dup&#259; caz, responsabili cu opera&#355;iunile\nprev&#259;zute la alin. (3) pot formula obiec&#355;ii ori refuza efectuarea\nacestora în condi&#355;iile art. 490, respectiv art. 553.</span></p>\n<p class=MsoNormal style='margin-top:1.3pt;margin-right:0in;margin-bottom:0in;\nmargin-left:0in'><span style='color:black'>(6)Prevederile alin. (1) -(5) se\naplic&#259; &#351;i în cazul altor acte administrative sau asimilate acestora\nîn condi&#355;iile legii emise, respectiv adoptate de autorit&#259;&#355;ile\nadministra&#355;iei publice locale.</span></p>"}